setup.py
src/sentiic3.py
src/sentiic3.egg-info/PKG-INFO
src/sentiic3.egg-info/SOURCES.txt
src/sentiic3.egg-info/dependency_links.txt
src/sentiic3.egg-info/top_level.txt