Metadata-Version: 2.1
Name: sentiic3
Version: 0.0.3
Summary:  Sentimental Analysis From Social Media
Author: DUMPA NAVEEN KUMAR REDDY
Author-email: naveenkumarreddydumpa@gmail.com
